<?xml version="1.0" encoding="utf-8" ?>
<Defs>

  <ThingDef ParentName="PlantBase">
    <defName>BMT_Clathropteris</defName>
    <label>clathropteris</label>
    <description>The first recorded dipterid fern.</description>
    <statBases>
      <MaxHitPoints>150</MaxHitPoints>
      <Nutrition>0.25</Nutrition>
    </statBases>
    <graphicData>
      <texPath>BMT_Prehistoric/Plant/Clathropteris</texPath>
      <graphicClass>Graphic_Random</graphicClass>
    </graphicData>
    <selectable>true</selectable>
    <pathCost>30</pathCost>
    <ingestible />
    <plant>
      <fertilityMin>0.5</fertilityMin>
      <!--fertilitySensitivity>0</fertilitySensitivity-->
      <growDays>2.5</growDays>
      <visualSizeRange>1.5~2</visualSizeRange>
      <topWindExposure>0.3</topWindExposure>
      <wildClusterRadius>4</wildClusterRadius>
      <wildClusterWeight>4</wildClusterWeight>
      <wildOrder>2</wildOrder>
    </plant>
  </ThingDef>

</Defs>