<?xml version="1.0" encoding="utf-8" ?>
<Patch>
<!--
BMT_Ammonite - All island and shorelines except the coldest.
BMT_GiantAmmonite - All island and shorelines except the coldest (same as BMT_Ammonite).
BMT_Coelacanth - Warmer coasts and islands.
BMT_Dimorphodon - All lusher biomes except the coldest.
BMT_Diplocaulus - Warm to cool biomes with rivers.
BMT_Elasmosaurus - All warmer to cool islands and shorelines. 
BMT_Liopleurodon - Cold (But not freezing) to temperate islands and shores
BMT_Pteranodon - All warmer to cool biomes with LAKE OR OCEAN tile next to it. 
-->
	<Operation Class="PatchOperationAdd">
		<xpath>Defs/BiomeDef[defName="TemperateForest"]/wildAnimals</xpath>
		<value> 
		    <BMT_Dimorphodon>0.5</BMT_Dimorphodon>
		    <BMT_Elasmosaurus>0.3</BMT_Elasmosaurus>
		    <BMT_Liopleurodon>0.3</BMT_Liopleurodon>
		    <BMT_Pteranodon>0.5</BMT_Pteranodon>
			<BMT_Diplocaulus>0.5</BMT_Diplocaulus>
		</value>
	</Operation>
	
	<Operation Class="PatchOperationAdd">
		<xpath>Defs/BiomeDef[defName="TemperateSwamp"]/wildAnimals</xpath>
		<value>				
		    <BMT_Dimorphodon>0.5</BMT_Dimorphodon>
		    <BMT_Elasmosaurus>0.2</BMT_Elasmosaurus>
		    <BMT_Liopleurodon>0.2</BMT_Liopleurodon>
			<BMT_Pteranodon>0.5</BMT_Pteranodon>
			<BMT_Diplocaulus>0.5</BMT_Diplocaulus>
		</value>
	</Operation>


	<Operation Class="PatchOperationAdd">
		<xpath>Defs/BiomeDef[defName="TropicalRainforest"]/wildAnimals</xpath>
		<value>
		    <BMT_Dimorphodon>0.5</BMT_Dimorphodon>
			<BMT_Elasmosaurus>0.2</BMT_Elasmosaurus>
		    <BMT_Liopleurodon>0.3</BMT_Liopleurodon>
		    <BMT_Pteranodon>0.5</BMT_Pteranodon>
			<BMT_Diplocaulus>0.5</BMT_Diplocaulus>
		</value>
	</Operation>

	<Operation Class="PatchOperationAdd">
		<xpath>Defs/BiomeDef[defName="TropicalSwamp"]/wildAnimals</xpath>
		<value>
		    <BMT_Dimorphodon>0.5</BMT_Dimorphodon>
			<BMT_Elasmosaurus>0.2</BMT_Elasmosaurus>
		    <BMT_Liopleurodon>0.3</BMT_Liopleurodon>
		    <BMT_Pteranodon>0.5</BMT_Pteranodon>
			<BMT_Diplocaulus>0.5</BMT_Diplocaulus>
		</value>
	</Operation>
	
		<Operation Class="PatchOperationAdd">
		<xpath>Defs/BiomeDef[defName="BorealForest"]/wildAnimals</xpath>
		<value>
		    <BMT_Dimorphodon>0.2</BMT_Dimorphodon>
			<BMT_Elasmosaurus>0.2</BMT_Elasmosaurus>
		    <BMT_Liopleurodon>0.4</BMT_Liopleurodon>
		    <BMT_Pteranodon>0.5</BMT_Pteranodon>
			<BMT_Diplocaulus>0.5</BMT_Diplocaulus>
		</value>
	</Operation>
	
		<Operation Class="PatchOperationAdd">
		<xpath>Defs/BiomeDef[defName="ColdBog"]/wildAnimals</xpath>
		<value>
		    <BMT_Dimorphodon>0.2</BMT_Dimorphodon>
			<BMT_Elasmosaurus>0.3</BMT_Elasmosaurus>
		    <BMT_Liopleurodon>0.4</BMT_Liopleurodon>
		    <BMT_Pteranodon>0.5</BMT_Pteranodon>
			<BMT_Diplocaulus>0.2</BMT_Diplocaulus>
		</value>
	</Operation>
	
	<Operation Class="PatchOperationAdd">
		<xpath>Defs/BiomeDef[defName="Tundra"]/wildAnimals</xpath>
		<value>
			<BMT_Elasmosaurus>0.3</BMT_Elasmosaurus>
		    <BMT_Liopleurodon>0.4</BMT_Liopleurodon>
		    <BMT_Pteranodon>0.3</BMT_Pteranodon>
		</value>
	</Operation>
	
	<Operation Class="PatchOperationAdd">
		<xpath>Defs/BiomeDef[defName="BiomesIslands_Atoll"]/wildAnimals</xpath>
		<value> 
		    <BMT_Dimorphodon>0.5</BMT_Dimorphodon>
			<BMT_Elasmosaurus>0.3</BMT_Elasmosaurus>
			<BMT_Coelacanth>0.5</BMT_Coelacanth>
			<BMT_GiantAmmonite>0.5</BMT_GiantAmmonite>
		    <BMT_Ammonite>0.6</BMT_Ammonite>
			<BMT_Liopleurodon>0.2</BMT_Liopleurodon>
		    <BMT_Pteranodon>0.5</BMT_Pteranodon>
		</value>
	</Operation>
	
		<Operation Class="PatchOperationAdd">
		<xpath>Defs/BiomeDef[defName="BiomesIslands_BorealIsland"]/wildAnimals</xpath>
		<value>
		    <BMT_Dimorphodon>0.5</BMT_Dimorphodon>
			<BMT_Elasmosaurus>0.3</BMT_Elasmosaurus>
         	<BMT_Liopleurodon>0.5</BMT_Liopleurodon>
		    <BMT_Pteranodon>0.5</BMT_Pteranodon>
		</value>
	</Operation>


<!--
	<Operation Class="PatchOperationAdd">
		<xpath>Defs/BiomeDef[defName="AridShrubland"]/wildAnimals</xpath>
		<value>
			<BMT_Parasaur>0.4</BMT_Parasaur>
		</value>
	</Operation>
-->

<!--
	<Operation Class="PatchOperationAdd">
		<xpath>Defs/BiomeDef[defName="Desert"]/wildAnimals</xpath>
		<value>
		    <BMT_Velociraptor>0.5</BMT_Velociraptor>
		</value>
	</Operation>
	-->
	


<!--
	<Operation Class="PatchOperationAdd">
		<xpath>Defs/BiomeDef[defName="ExtremeDesert"]/wildAnimals</xpath>
		<value>
			<BMT_Dilophosaurus>0.05</BMT_Dilophosaurus> 
		</value>
	</Operation>
	-->
	
	<!--
	<Operation Class="PatchOperationAdd">
		<xpath>Defs/BiomeDef[defName="IceSheet"]/wildAnimals</xpath>
		<value>
			<Placeholder>99999999</Placeholder>
		</value>
	</Operation>
	
	<Operation Class="PatchOperationAdd">
		<xpath>Defs/BiomeDef[defName="SeaIce"]/wildAnimals</xpath>
		<value>
			<Placeholder>99999999</Placeholder>
		</value>
	</Operation>
	-->
</Patch>